{"1h": {"vwma": ["XAG", "DOGE", "NVDA", "CL", "SNDK", "CRCL", "TSLA", "NEAR", "BZ", "BNB", "LINK", "CRV", "AVAX", "WLD", "DOT", "COIN", "LITE", "AMD", "PENDLE", "ETHFI", "PIEVERSE", "EWY", "QQQ"], "channel": ["BTC", "ETH", "SOL", "XAU", "XRP", "SUI", "CL", "XAUT", "HYPE", "TSLA", "PEPE", "TON", "BZ", "ADA", "BNB", "TAO", "AAVE", "PAXG", "AVAX", "USELESS", "MSTR", "LTC", "SHIB", "PENGU", "VVV", "BCH", "LUNC", "COIN", "FARTCOIN", "XLM", "GOOGL", "HBAR", "SEI", "FET", "MSFT", "QQQ"], "best": ["BZ", "USELESS"]}, "4h": {"vwma": ["BTC", "XAU", "XRP", "TRUMP", "XAUT", "PEPE", "AAVE", "PAXG", "FIL", "LTC", "SHIB", "OPG", "FARTCOIN", "GOOGL", "HBAR", "FET", "LDO", "CHZ", "PUMP", "ALGO"], "channel": ["BTC", "ETH", "XAU", "SNDK", "INTC", "XAUT", "HYPE", "PEPE", "TAO", "PAXG", "SHIB", "BCH", "LUNC", "FARTCOIN", "VIRTUAL", "ORDI", "GOOGL", "ASTER", "PUMP", "MSFT", "QQQ"], "best": ["HYPE", "FARTCOIN", "MSFT"]}}