{"1h": {"vwma": ["BTC", "ETH", "XAG", "SOL", "XRP", "TAO", "TSLA", "DOGE", "CRCL", "SUI", "ADA", "COIN", "ZEC", "LINK", "BNB", "NVDA", "MSTR", "BCH", "AVAX", "AMZN", "NEAR", "SHIB", "AAVE", "UNI", "AAPL", "PENGU", "XLM", "LTC", "WLD", "HBAR", "VIRTUAL", "HOOD", "RENDER", "QQQ", "XPL", "XMR", "TURBO", "CYS", "G", "1000BONK", "ETC"], "channel": ["CL", "ENA", "BCH", "MU", "DOT", "ASTER", "AAPL", "TRX", "GUN", "QQQ", "GOOGL", "BGB", "XMR", "MSFT", "CYS"], "best": ["ASTER"]}, "4h": {"vwma": ["BTC", "ETH", "XRP", "PEPE", "HYPE", "DOGE", "COIN", "LINK", "AMZN", "FIL", "FARTCOIN", "XLM", "LTC", "TRX", "RENDER", "ETC"], "channel": ["XAU", "XAUT", "PAXG", "HYPE", "NVDA", "MU", "DOT", "ASTER", "TRX", "QQQ", "GOOGL", "BGB", "XPT", "OP", "MSFT", "ETHFI"], "best": ["ASTER", "BGB"]}}