{"1h": {"vwma": ["ETH", "SOL", "XAU", "XAUT", "PAXG", "BNB", "NEAR", "PUMP", "TRUMP", "VIRTUAL", "ASTER", "KITE", "XMR", "LAYER", "OP", "PI", "XPL", "USELESS", "CRCL", "PNUT"], "channel": ["XAU", "XAUT", "PAXG", "PI", "TSLA", "ARM", "MORPHO", "TRX", "BGB"], "best": ["TSLA", "MORPHO"]}, "4h": {"vwma": ["ETH", "SOL", "DOT", "LINK", "BNB", "AVAX", "SIREN", "TRUMP", "ASTER", "ALICE", "APT", "MSTR", "XMR", "CRV", "XPL", "ARM"], "channel": ["NVDA", "TSLA", "ARM", "MORPHO", "TRX"], "best": ["XMR", "BGB"]}}