{"1h": {"vwma": ["CL", "BZ", "WLD", "TSLA", "DASH", "ONT", "NVDA", "ARB", "UAI", "VVV", "KITE", "BLUR", "M", "TRX"], "channel": ["BTC", "ETH", "SOL", "XRP", "HYPE", "PEPE", "XAU", "DOGE", "ADA", "SUI", "XAUT", "XAG", "WLD", "LINK", "BNB", "ENA", "AAPL", "NEAR", "SHIB", "PAXG", "FIL", "LTC", "AVAX", "DASH", "XPL", "DOT", "AAVE", "BCH", "RENDER", "PENGU", "1000BONK", "PUMP", "CRV", "NVDA", "HBAR", "VIRTUAL", "ARB", "APT", "ONDO", "MSTR", "EDGE", "XLM", "ID", "UNI", "VVV", "WIF", "XMR", "CFX", "ASTER", "POL", "TRX"], "best": ["CL", "XAU", "XAUT", "XAG", "BNB", "TSLA", "AAPL", "PAXG", "MON", "NVDA", "APT", "MSTR", "EDGE", "POL"]}, "4h": {"vwma": ["BTC", "PEPE", "XAU", "AIN", "SUI", "XAUT", "XAG", "FARTCOIN", "ENA", "AAPL", "PAXG", "FIL", "RENDER", "PENGU", "PUMP", "MSTR", "WIF", "CYS", "CROSS", "XMR", "PIXEL", "TRX"], "channel": ["XAU", "DOGE", "XAUT", "NOM", "AAPL", "SHIB", "PAXG", "BCH", "RENDER", "WLFI", "ONDO", "XLM", "ASTER", "POL", "ALGO", "TRX"], "best": ["XAUT", "PAXG", "PIXEL"]}}