{"1h": {"vwma": ["BTC", "ETH", "XAU", "XAG", "XRP", "DOGE", "XAUT", "HYPE", "PEPE", "TSLA", "BZ", "PAXG", "SUI", "ADA", "COIN", "AAPL", "LUNC", "SHIB", "RIVER", "AMZN", "ENSO", "ONDO", "WIF", "PLTR", "FARTCOIN", "VIRTUAL", "QQQ", "BCH", "API3", "SIREN", "TON", "XMR"], "channel": ["XAU", "SOL", "CL", "DOGE", "XAUT", "NVDA", "BZ", "TRUMP", "PAXG", "ADA", "LINK", "AAPL", "NEAR", "AAVE", "LUNC", "GOOGL", "SHIB", "H", "BNB", "WLD", "DOT", "AVAX", "FIL", "APT", "MSFT", "LTC", "QQQ", "CC", "KAT", "TON", "XMR"], "best": ["APT", "CC"]}, "4h": {"vwma": ["BTC", "PEPE", "TSLA", "CRCL", "SHIB", "AMZN", "ENSO", "ONDO", "APT", "PLTR", "QQQ", "BCH", "PI", "XMR"], "channel": ["BTC", "XAU", "SOL", "XAUT", "PAXG", "LINK", "NEAR", "BNB", "AMZN", "AVAX", "MSFT", "LTC", "QQQ", "BCH", "M", "META", "XMR"], "best": []}}