{"1h": {"vwma": ["BTC", "ETH", "SOL", "LAB", "TON", "TSLA", "PEPE", "LINK", "INJ", "BNB", "CRCL", "ASTER", "AVAX", "BCH", "DOT", "AAVE", "QQQ", "ENA", "LTC", "FIL", "TIA", "XMR", "1000BONK", "COIN", "TRX", "PUMP", "PENDLE", "VIRTUAL", "XPL", "FARTCOIN", "ORDI", "FLY", "APT"], "channel": ["BTC", "XAU", "XAG", "XRP", "CL", "NVDA", "XAUT", "BZ", "CBRS", "PAXG", "ADA", "CRCL", "RKLB", "CHZ", "GOOGL", "QQQ", "COIN", "TRX", "ARB", "MSFT", "H"], "best": ["DOT", "AAVE", "TRX"]}, "4h": {"vwma": ["CL", "NVDA", "ONDO", "MU", "SNDK", "INTC", "TSLA", "DASH", "ASTER", "SAHARA", "QQQ", "RENDER", "EWY", "TRX", "MSFT"], "channel": ["BTC", "XAU", "XRP", "NVDA", "XAUT", "PAXG", "BNB", "RKLB", "CHZ", "GOOGL", "QQQ", "LTC", "RIVER", "TRX", "MSFT"], "best": ["CHZ"]}}