{"1h": {"vwma": ["TSLA", "PUMP", "XAUT", "PAXG", "XAU", "STX", "ATOM", "KAITO", "TRX", "CYS"], "channel": ["BTC", "ETH", "SOL", "DOGE", "TAO", "LINK", "HYPE", "WLFI", "BCH", "XAUT", "LTC", "BNB", "AVAX", "DOT", "ZEN", "MSTR", "PAXG", "NVDA", "PIEVERSE", "XAU", "ARB", "TON", "OP", "B", "MON", "ACH", "BGB", "TRX", "GALA", "AAPL", "CRV", "ETC"], "best": ["ETH", "DOGE", "HYPE", "PIEVERSE"]}, "4h": {"vwma": ["BTC", "ETH", "XRP", "DOGE", "RIVER", "ADA", "LINK", "ENA", "WLFI", "BCH", "XAUT", "LTC", "BNB", "AVAX", "NEAR", "AAVE", "SHIB", "XLM", "PAXG", "WAL", "MAGIC", "FIL", "TRUMP", "SEI", "ICP", "XAU", "ARB", "APT", "TON", "MON", "KAITO", "EIGEN", "JUP", "CRV", "ETC", "XVG", "PNUT", "PENDLE"], "channel": ["BTC", "ETH", "ZEC", "RIVER", "LINK", "HYPE", "WLFI", "BCH", "UNI", "LTC", "HBAR", "BNB", "XPL", "AVAX", "DOT", "ASTER", "NEAR", "ZEN", "NVDA", "SEI", "DYDX", "ZK", "ARB", "APT", "MON", "BGB", "AAPL", "CRV", "XVG", "PENDLE"], "best": ["RIVER", "HYPE", "TON"]}}