{"1h": {"vwma": ["BTC", "CL", "SOL", "SNDK", "XRP", "HYPE", "BZ", "DOGE", "SUI", "ADA", "PEPE", "CRCL", "MRVL", "CBRS", "WLD", "TSEM", "NVDA", "AAVE", "UNI", "AMD", "QQQ", "ZHIPU", "BNB", "ONDO", "ENA", "AVAX", "GLW", "PLTR", "XPL", "LTC", "DOT", "INJ", "TRUMP", "FIL", "EGLD", "NATGAS", "TIA", "HBAR", "AMZN"], "channel": ["CL", "XAU", "SPCX", "XAG", "BZ", "XAUT", "TAO", "DEXE", "QQQ", "MSFT", "TSLA", "PAXG", "EGLD", "NATGAS", "META", "UVXY", "AMZN"], "best": ["AVAX"]}, "4h": {"vwma": ["SOL", "XRP", "HYPE", "DOGE", "MSTR", "WLD", "QQQ", "BNB", "AVAX", "PLTR", "FARTCOIN", "MSFT", "LTC", "DOT", "FIL", "ARB", "M", "AMZN"], "channel": ["XAU", "XAG", "XAUT", "TAO", "QQQ", "BCH", "MSFT", "PAXG", "ARM", "AMZN"], "best": ["WLD", "FARTCOIN"]}}