{"1h": {"vwma": ["ETH", "DASH", "BERA", "ME", "HYPE", "LTC", "BNB", "SAFE", "CHZ", "VANRY", "AAVE", "PIPPIN", "BIGTIME", "MERL", "TRX", "GALA", "MET", "MOVE", "GMT", "ARB", "ZKP", "DRIFT", "LIT", "TON", "ID", "XAUT", "XAG", "BIO"], "channel": ["ETH", "BTC", "SOL", "XRP", "PUMP", "BNB", "LINK", "CHZ", "VIRTUAL", "TRUMP", "TRX", "FET", "BCH", "PENGU", "CRV", "SEI", "XAUT", "XAG"], "best": ["PUMP", "BNB", "BIGTIME", "PENGU", "ARB"]}, "4h": {"vwma": ["BTC", "SOL", "AXS", "LINK", "DOT", "EGLD", "MET", "WLFI", "ARB", "OP", "XAUT", "BIO"], "channel": ["BTC", "SOL", "NEAR", "BNB", "TAO", "TRUMP", "POL", "KAITO", "DYDX", "XAUT"], "best": ["KAITO"]}}