{"1h": {"vwma": ["BTC", "SOL", "XAG", "XAU", "CL", "DOGE", "NVDA", "MU", "CRCL", "XAUT", "TRUMP", "BZ", "BNB", "CHIP", "OPG", "COIN", "LITE", "PENDLE", "PIEVERSE", "DOT", "XMR", "ETHFI", "CHZ"], "channel": ["BTC", "ETH", "SOL", "XAU", "XRP", "SUI", "CL", "DOGE", "NVDA", "XAUT", "TSLA", "PEPE", "HYPE", "ADA", "H", "BZ", "TAO", "LINK", "PAXG", "AAVE", "VVV", "AVAX", "MSTR", "SHIB", "WLD", "OPG", "LUNC", "PENGU", "LTC", "BCH", "FARTCOIN", "COIN", "SEI", "XLM", "FET", "HBAR", "GOOGL", "XMR", "QQQ", "MSFT"], "best": ["SOL", "AAVE", "MSTR", "PENGU", "COIN", "LITE"]}, "4h": {"vwma": ["BTC", "XAU", "XRP", "DOGE", "XAUT", "TON", "PEPE", "TRUMP", "PAXG", "AAVE", "FIL", "SHIB", "VIRTUAL", "LTC", "NAORIS", "XLM", "HBAR", "ALGO", "GOOGL", "PUMP", "BIO", "XMR", "CHZ"], "channel": ["BTC", "ETH", "SNDK", "INTC", "PEPE", "HYPE", "TAO", "SHIB", "LUNC", "VIRTUAL", "BCH", "FARTCOIN", "ORDI", "ASTER", "GOOGL", "EWY", "QQQ", "MSFT"], "best": ["HYPE", "LTC", "BCH", "FARTCOIN", "MSFT"]}}