{"1h": {"vwma": ["XRP", "SPY", "BSB", "PEPE", "ADA", "TAO", "AAVE", "LINK", "ASTER", "AVAX", "ORDI", "BNB", "VIRTUAL", "GALA", "XAU", "RIVER", "TRUMP", "FARTCOIN", "LTC", "WLD", "FET", "PYTH", "CFG", "HBAR", "BASED", "DOT", "TRX", "XAG", "ETC", "CHZ", "ALGO"], "channel": ["BTC", "SOL", "XRP", "SPY", "HYPE", "FIL", "PEPE", "ICP", "ADA", "TAO", "ENA", "LINK", "AVAX", "NEAR", "BNB", "VIRTUAL", "NOT", "GALA", "OP", "XAU", "XLM", "TRUMP", "FARTCOIN", "SHIB", "LTC", "PUMP", "WLD", "FET", "WLFI", "CFG", "HBAR", "XPL", "APT", "ARB", "DOT", "DIA", "1000BONK", "TRX", "XAG", "ETC", "INJ", "CHZ", "ALGO"], "best": []}, "4h": {"vwma": ["BTC", "ETH", "XRP", "DOGE", "SPY", "HYPE", "DYM", "AAVE", "BNB", "XAU", "RIVER", "DEEP", "SHIB", "LTC", "HBAR", "ZEN", "DIA", "ACE"], "channel": ["BTC", "DOGE", "SPY", "CL", "SHIB", "BZ", "BCH"], "best": ["BTC", "CL", "BZ"]}}