{"1h": {"vwma": ["BTC", "SOL", "XAU", "XAUT", "PAXG", "DOT", "BNB", "TAO", "NEAR", "AVAX", "ASTER", "MSTR", "PUMP", "VIRTUAL", "PENGU", "XMR", "TRUMP", "PI", "ATH", "XPL", "CRV", "ICP", "CRCL", "PENDLE", "0G", "BERA", "JUP", "CHZ"], "channel": ["XAU", "XAUT", "TSLA", "BGB", "ARM", "TRX", "WET"], "best": []}, "4h": {"vwma": ["SOL", "LINK", "BNB", "FIL", "AVAX", "ASTER", "LTC", "MSTR", "HBAR", "XMR", "ZRO", "ATH", "CRV", "PENDLE", "JUP", "ARM"], "channel": ["TSLA", "NVDA", "ARM", "TRX"], "best": ["GRASS", "JUP"]}}