{"1h": {"vwma": ["XAUT", "XAG", "SXT", "PAXG", "XAU", "WLFI", "ACH", "ALCH", "PENDLE", "SSV", "FUTU", "PLTR"], "channel": ["BTC", "ETH", "XRP", "MSTR", "BNB", "XAG", "BERA", "TSLA", "NVDA", "CRCL", "FRAX", "GOOGL", "AAPL", "HOOD", "QQQ", "TRX", "COIN", "FUTU", "META", "PLTR"], "best": []}, "4h": {"vwma": ["SAND", "SSV"], "channel": ["BTC", "SOL", "DOGE", "SUI", "ADA", "MSTR", "LINK", "LTC", "ENA", "PUMP", "TSLA", "ASTER", "NVDA", "AVAX", "CRCL", "AAVE", "WLD", "NEAR", "DOT", "GOOGL", "APT", "AAPL", "SEI", "OP", "FIL", "DYDX", "QQQ", "ARB", "INJ", "COIN", "ATOM", "TIA", "META", "PLTR"], "best": ["MSTR", "TSLA", "ASTER", "NVDA", "CRCL", "WLD", "APT", "AAPL", "QQQ", "INJ", "COIN", "META"]}}