{"1h": {"vwma": ["BTC", "XRP", "SPY", "PEPE", "CHIP", "TAO", "ADA", "XAU", "AAVE", "AVAX", "ASTER", "BNB", "XAG", "XLM", "DOGS", "SHIB", "TRUMP", "LTC", "B", "HBAR", "DOT", "NVDA", "BASED", "XAUT", "ALGO", "TRX", "ETC", "CRV"], "channel": ["BTC", "SOL", "TON", "SPY", "STRK", "PEPE", "TAO", "ENA", "ADA", "XAU", "BNB", "NEAR", "XAG", "GALA", "VIRTUAL", "XLM", "SHIB", "1000BONK", "PUMP", "NOT", "TRUMP", "LTC", "FET", "HBAR", "XPL", "DOT", "NVDA", "XAUT", "ALGO", "TRX", "TSLA", "ETC"], "best": ["TON", "DOGS"]}, "4h": {"vwma": ["BTC", "ETH", "XRP", "DOGE", "SPY", "HYPE", "STRK", "XAU", "AAVE", "BNB", "SHIB", "JTO", "RIVER", "LTC", "HBAR", "ZEN", "XAUT"], "channel": ["DOGE", "SPY", "CL", "BZ", "LUNC", "BCH"], "best": ["DOGE"]}}