{"1h": {"vwma": ["XRP", "TAO", "XAU", "ZEC", "ADA", "BCH", "PI", "XAUT", "HBAR", "UNI", "FARTCOIN", "PUMP", "XPL", "AVAX", "NEAR", "PAXG", "IP", "MOVE", "VIRTUAL", "ONDO", "RENDER", "DOT", "DYDX", "NIL", "MERL", "CRV", "WAVES", "LIT", "TON", "TNSR"], "channel": ["BTC", "ETH", "SOL", "DOGE", "XAU", "HYPE", "PIPPIN", "SUI", "ADA", "LINK", "BCH", "ASTER", "TRUMP", "BNB", "APT", "PI", "SHIB", "XAUT", "HBAR", "WLFI", "FARTCOIN", "AAVE", "WLD", "LTC", "PENGU", "PUMP", "AVAX", "NEAR", "ENA", "PAXG", "WIF", "XLM", "ONDO", "RENDER", "SEI", "ARB", "1000BONK", "TSLA", "DOT", "COMP", "DYDX", "LUNA", "GALA", "CRV", "FIL", "WAVES", "LIT", "TON", "ZKP", "STORJ", "ICP", "RESOLV", "MSTR"], "best": ["TON"]}, "4h": {"vwma": ["XRP", "XAU", "ADA", "SHIB", "XAUT", "WLD", "PENGU", "PAXG", "MOVE", "OM", "XLM", "RENDER", "1000BONK", "TSLA", "LUNA", "NIL", "0G", "WAVES", "LIT", "SAGA"], "channel": [], "best": ["IP"]}}