{"1h": {"vwma": ["BTC", "SOL", "XRP", "SUI", "ZEC", "BNB", "CLO", "TAO", "VIRTUAL", "XAUT", "ASTER", "NVDA", "XAG", "AAPL", "FET", "XPL", "TRUMP", "PAXG", "BGB", "GOOGL", "CRCL", "XAU", "ATOM", "CYS", "SLV", "COIN", "ACH", "TRX"], "channel": ["TSLA", "XAUT", "NVDA", "AAPL", "QQQ", "PAXG", "GOOGL", "XAU", "AMZN", "MSFT"], "best": ["TRX"]}, "4h": {"vwma": ["XRP", "HBAR", "HYPE", "1000BONK", "XAUT", "POL", "ONDO", "QQQ", "PAXG", "BGB", "ICNT", "CRCL", "GMT", "XAU", "AMZN"], "channel": ["LTC", "BCH", "NVDA", "QQQ", "AMZN", "TRX", "MSFT"], "best": ["XRP", "HYPE", "LTC", "ONDO", "ZEREBRO", "CRCL", "TRX"]}}