{"1h": {"vwma": ["SOL", "XAU", "XAUT", "JTO", "PROS", "SUI", "PEPE", "PAXG", "LINK", "ADA", "GALA", "BNB", "AVAX", "TRUMP", "AAVE", "LTC", "XLM", "SHIB", "SPK", "TRX", "QQQ", "OPG"], "channel": ["BTC", "ETH", "SOL", "XAU", "XRP", "XAUT", "PAXG", "LINK", "BNB", "HOOD", "TRUMP", "AAOI", "MSTR", "PI", "MEGA", "LTC", "FARTCOIN", "SHIB", "BCH", "TRX", "QQQ", "ALGO", "USUAL", "XMR"], "best": ["XLM", "TRX"]}, "4h": {"vwma": ["BTC", "XAU", "XAUT", "DOGE", "PAXG", "HYPE", "BNB", "MSTR", "LTC", "M", "SHIB", "USUAL", "XMR"], "channel": ["BTC", "ETH", "CL", "BZ", "DOGE", "PENGU", "PI", "SHIB", "BCH", "XMR"], "best": ["BZ", "PI"]}}