{"1h": {"vwma": ["BTC", "ETH", "SKHYNIX", "XAG", "DRAM", "VELVET", "PEPE", "SUI", "XLM", "TAO", "BCH", "LINK", "XAUT", "DOT", "TSLA", "EWY", "FIL", "BNB", "KAT", "GLW", "AVAX", "ONDO", "QQQ", "LTC", "GRAM", "AMZN", "TIA", "ICP", "ORDI", "INJ"], "channel": ["CL", "XAU", "BZ", "XAUT", "PAXG", "AMZN", "TIA", "HOOD", "NATGAS", "ICP", "KAITO", "MSFT", "GOOGL", "ORDI"], "best": ["DRAM", "TIA", "NATGAS", "KAITO"]}, "4h": {"vwma": ["KORU", "SNDK", "SOL", "XRP", "XAU", "HYPE", "XAG", "SUI", "ADA", "TAO", "BZ", "XAUT", "DOT", "TSLA", "BNB", "ENA", "AVAX", "ONDO", "QQQ", "LTC", "EDGE", "GRAM", "PAXG", "AMZN", "COIN", "KAITO", "MSFT", "GOOGL", "ORDI"], "channel": ["SOL", "XAU", "XAUT", "AVAX", "PAXG", "KAITO", "MSFT", "GOOGL"], "best": []}}