{"1h": {"vwma": ["TAO", "NVDA", "XAUT", "BABY", "ZEN", "GOOGL", "ACH", "FLOW", "KAITO", "TRX", "QQQ", "MSFT"], "channel": ["BTC", "ETH", "SOL", "XRP", "PEPE", "DOGE", "SUI", "ADA", "HBAR", "TSLA", "LINK", "HYPE", "BCH", "BNB", "MSTR", "TAO", "ENA", "UNI", "VIRTUAL", "XPL", "NVDA", "XAUT", "WIF", "ASTER", "LTC", "RENDER", "WLD", "NEAR", "AAVE", "PUMP", "AVAX", "DOT", "SHIB", "PENGU", "PIEVERSE", "FIL", "FET", "JASMY", "ONDO", "TRUMP", "GOOGL", "AAPL", "XLM", "SEI", "APT", "ARB", "INJ", "PAXG", "IP", "ICP", "KAS", "DYDX", "XAU", "TIA", "TON", "CRV", "ETC", "ZK", "LIGHT", "MOODENG", "GIGGLE", "BGB", "GALA", "ORDI", "MON", "TRX", "PNUT", "STRK", "QQQ", "ETHFI", "MSFT", "OP"], "best": ["PEPE", "ADA", "HBAR", "TSLA", "ENA", "UNI", "ASTER", "PENGU", "ZEN", "FET", "AAPL"]}, "4h": {"vwma": ["BTC", "ETH", "XRP", "HBAR", "LINK", "BCH", "BNB", "1000BONK", "NVDA", "XAUT", "LTC", "BROCCOLI", "ZEN", "ONDO", "TRUMP", "GOOGL", "XLM", "IP", "XAU", "ETC", "ZK", "BGB", "TRX", "STRK", "QQQ", "ETHFI"], "channel": ["BTC", "TSLA", "BNB", "UNI", "NVDA", "ASTER", "LTC", "GOOGL", "AAPL", "APT", "TON", "BGB", "ORDI", "MON", "LYN", "QQQ", "MSFT"], "best": ["ZEC", "UNI", "ZEN", "BGB"]}}