{"1h": {"vwma": ["XAG", "XAU", "BABY", "NAORIS", "STEEM", "PAXG", "ZRO", "LYN", "TRX", "KAVA", "M"], "channel": ["XAUT", "UAI", "XAG", "XAU", "PI", "BNB", "FIL", "AAVE", "DOT", "TSLA", "BCH", "LTC", "APT", "ASTER", "AVAX", "ARB", "PIPPIN", "PAXG", "VIRTUAL", "NVDA", "UNI", "HBAR", "TRX", "SENT", "SEI", "TIA", "XMR", "TON", "AAPL", "M", "ATOM"], "best": ["BTC", "SOL", "XAUT", "XAG", "XAU", "LINK", "BNB", "DOT", "TSLA", "BCH", "LTC", "MSTR", "ASTER", "AVAX", "ARB", "PIPPIN", "PAXG", "WLD", "VIRTUAL", "NVDA", "UNI", "HBAR", "SEI", "TIA", "MU", "AAPL", "SPX", "ATOM"]}, "4h": {"vwma": ["RIVER", "HYPE", "TAO", "NEAR", "PUMP", "TRX", "TON"], "channel": ["BTC", "ETH", "SOL", "XAUT", "ADA", "XAU", "LINK", "BNB", "FIL", "AAVE", "TSLA", "LTC", "MSTR", "ASTER", "PAXG", "WLD", "TRUMP", "UNI", "HBAR", "SEI", "XMR", "MU", "AAPL"], "best": ["TAO", "TRUMP", "SEI", "AAPL"]}}