{"1h": {"vwma": ["BTC", "ETH", "SKHYNIX", "MU", "SKHY", "XAG", "DRAM", "VELVET", "DOGE", "SUI", "XLM", "US", "TAO", "BCH", "LINK", "XAUT", "DOT", "TSLA", "EWY", "FIL", "BNB", "KAT", "GLW", "AVAX", "RAM", "ONDO", "LTC", "QQQ", "AAOI", "ETHFI", "GRAM", "PAXG", "AMZN", "TIA", "ORDI", "ICP", "INJ"], "channel": ["CL", "XAU", "BZ", "XAUT", "SYN", "PAXG", "AMZN", "NATGAS", "HOOD", "TIA", "ORDI", "KAITO", "ICP", "GOOGL"], "best": ["EWY", "SYN", "KAITO", "GOOGL"]}, "4h": {"vwma": ["KORU", "SOL", "XRP", "XAU", "HYPE", "XAG", "MSTR", "ADA", "TAO", "BZ", "XAUT", "DOT", "TSLA", "BNB", "AVAX", "ONDO", "LTC", "QQQ", "EDGE", "PUMP", "GRAM", "PAXG", "AMZN", "ORDI", "COIN", "KAITO", "GOOGL"], "channel": ["SOL", "XAU", "XAUT", "PAXG", "KAITO"], "best": ["ADA"]}}