{"4h": {"vwma": ["BTC", "ETH", "SOL", "XRP", "COIN", "ZEC", "ADA", "BCH", "SAHARA", "NEAR", "ENJ", "APT", "DOT", "VIRTUAL", "SHIB", "PLTR", "PENGU", "LTC", "GOOGL", "XLM", "RDDT"], "channel": ["BTC", "XAU", "XAUT", "BNB", "TSLA", "PAXG", "SUI", "LINK", "NVDA", "AVAX", "AAPL", "PUMP", "ASTER", "AMZN", "UNI", "WLFI", "TRX", "BABA", "ETHFI", "ZRO", "TON", "QQQ", "META"], "best": ["TAO", "TSLA", "BCH", "SHIB", "WLFI", "APR", "BABA", "TON", "ZETA", "META"]}, "1h": {"vwma": ["COIN", "BCH", "FET", "SAHARA", "APT", "PLTR", "KAS", "TRX", "WAXP"], "channel": ["XAUT", "HYPE", "TSLA", "CRCL", "NVDA", "MU", "BEAT", "AAPL", "PLTR", "AMZN", "AIN", "KAS", "WLFI", "GOOGL", "TRX", "BABA", "RDDT", "TON", "HOOD", "QQQ", "META"], "best": ["PIPPIN", "FET", "APT", "WLFI", "APR", "WAXP"]}}