{"1h": {"vwma": ["XAU", "XAG", "XAUT", "TAO", "PEPE", "ONT", "ONG", "DOGE", "ADA", "AAPL", "NVDA", "PAXG", "COIN", "FET", "FIL", "NEAR", "HBAR", "FARTCOIN", "AVAX", "AMZN", "SHIB", "PUMP", "DOT", "SEI", "HOOD", "WIF", "MSFT", "GAS", "EWY", "QQQ", "0G"], "channel": ["BTC", "ETH", "XAU", "XRP", "TSLA", "XAUT", "ONT", "AAPL", "NVDA", "SUI", "PAXG", "AMZN", "BCH", "ASTER", "HOOD", "NMR", "TRX", "XLM", "WIF", "MSFT", "QQQ", "0G"], "best": ["ADA", "COIN", "BCH"]}, "4h": {"vwma": ["XAU", "XAG", "XAUT", "TAO", "PEPE", "AAPL", "NVDA", "ZEC", "PAXG", "FET", "AMZN", "SHIB", "TRX", "WIF", "LIT", "QQQ", "0G"], "channel": ["BNB", "BCH", "DRIFT", "TRX"], "best": ["AAVE"]}}