{"1h": {"vwma": ["PRL", "CL", "TSLA", "AAVE", "INTC", "BASED", "BZ", "NAORIS", "CRV", "RIVER", "MU", "PI", "TSM", "JUP", "GOOGL", "MSFT", "SPY", "GIGGLE"], "channel": ["BTC", "ETH", "SOL", "XAU", "XRP", "XAG", "CL", "DOGE", "HYPE", "XAUT", "PEPE", "ZEC", "SUI", "TSLA", "AAVE", "TAO", "ADA", "MSTR", "CRCL", "LINK", "BZ", "HOOD", "BNB", "ENA", "NEAR", "FARTCOIN", "PAXG", "UNI", "DOT", "GWEI", "AVAX", "COIN", "LTC", "XLM", "CRV", "INJ", "BCH", "FIL", "WLD", "XPL", "VIRTUAL", "CHZ", "SHIB", "ONDO", "HBAR", "TON", "M", "PI", "SEI", "PUMP", "TSM", "ASTER", "GOOGL", "WIF", "XMR", "FET", "MSFT", "AMZN", "APT", "SPY"], "best": ["LTC", "M"]}, "4h": {"vwma": ["BTC", "DOGE", "PEPE", "ZEC", "LDO", "LAB", "AIN", "COIN", "LTC", "INJ", "BCH", "SHIB", "SONIC", "SKYAI", "SEI", "APT", "SPY"], "channel": ["BTC", "ETH", "SOL", "XAU", "XRP", "DOGE", "XAUT", "PEPE", "SUI", "TRUMP", "MSTR", "LINK", "BNB", "NEAR", "PAXG", "UNI", "GWEI", "AVAX", "COIN", "LTC", "XLM", "BCH", "FIL", "SHIB", "HBAR", "NOT", "ASTER", "MSFT", "AMZN", "APT", "SPY"], "best": ["SKYAI"]}}