{"1h": {"vwma": ["BTC", "ETH", "ZEC", "DOLO", "PUMP", "LINK", "XAG", "BNB", "XAUT", "NVDA", "ORDI", "XAU", "TRX", "SLV", "4", "PAXG", "ACT", "BGB"], "channel": ["BTC", "ETH", "SOL", "XRP", "DOGE", "ZEC", "LTC", "SUI", "ADA", "HYPE", "PUMP", "LINK", "XAG", "MSTR", "TSLA", "TAO", "FARTCOIN", "WLD", "BNB", "ASTER", "FIL", "UNI", "AVAX", "AAVE", "XAUT", "DOT", "HBAR", "NVDA", "AAPL", "NEAR", "ONDO", "XPL", "PENGU", "WIF", "1000BONK", "CYS", "XLM", "POWER", "FET", "SHIB", "XAU", "WLFI", "INJ", "ICNT", "APT", "GOOGL", "TRUMP", "COIN", "XVG", "SEI", "ARB", "TON", "DYDX", "OP", "ETC", "SLV", "PAXG", "ZK", "BGB"], "best": ["MSTR", "FARTCOIN", "AAPL", "1000BONK", "APT", "COIN", "TON"]}, "4h": {"vwma": ["SUI", "ADA", "LINK", "MSTR", "TAO", "BNB", "XAUT", "DOT", "NVDA", "NEAR", "PENGU", "WIF", "FET", "XAU", "RENDER", "INJ", "ICNT", "GOOGL", "DYDX", "ETC", "PAXG"], "channel": ["SOL", "BCH", "SUI", "KAITO", "TAO", "WLD", "BNB", "AVAX", "DOT", "AAPL", "NEAR", "XPL", "POL", "FET", "SHIB", "HOOD", "RENDER", "WLFI", "INJ", "GOOGL", "TRUMP", "COIN", "SEI", "TON", "DYDX", "ETC", "ZK"], "best": ["HOOD", "RENDER", "TON"]}}