{"1h": {"vwma": ["BTC", "ETH", "SOL", "XRP", "XAG", "XAU", "DOGE", "SUI", "TSLA", "SIGN", "ADA", "MSTR", "ZEC", "LINK", "XAUT", "NVDA", "ARC", "RESOLV", "SHIB", "AIN", "PAXG", "NEAR", "BNB", "FARTCOIN", "PUMP", "PENGU", "RENDER", "AAPL", "AAVE", "XPL", "ENA", "DOT", "XLM", "OPN", "BEAT", "HOOD", "ASTER", "LTC", "SAHARA", "ROBO", "1000BONK", "UNI", "AMZN", "ARB", "TIA", "ONDO", "META", "XMR", "WLFI", "ZRO", "GOOGL", "MSFT"], "channel": ["XAU", "FIL", "XAUT", "PAXG", "BCH", "KITE", "PLTR", "AAPL", "ASTER", "LTC", "HBAR", "ZRO", "ICP", "MSFT"], "best": ["ZEC", "RESOLV", "KITE"]}, "4h": {"vwma": ["BTC", "ETH", "SOL", "XRP", "XAG", "XAU", "TSLA", "MSTR", "LINK", "NVDA", "BNB", "PENGU", "VIRTUAL", "KITE", "MU", "XLM", "HOOD", "APT", "SAHARA", "ARM", "FET", "UNI", "AMZN", "TIA", "META", "GOOGL", "ICP", "MSFT"], "channel": ["PLTR", "WLD", "ICP", "MSFT"], "best": []}}