{"1h": {"vwma": ["BTC", "ETH", "SOL", "CL", "DOGE", "PEPE", "SUI", "HYPE", "ADA", "AAVE", "TAO", "AVAX", "XAG", "LINK", "ORDI", "ENA", "SHIB", "DOT", "FIL", "ONDO", "CRV", "HBAR", "SAND", "VIRTUAL", "SEI", "LTC", "FARTCOIN", "APT", "XPL", "UNI", "ASTER", "RENDER", "FET", "ARB", "NVDA"], "channel": ["BTC", "SOL", "XAUT", "XRP", "CL", "DOGE", "ZEC", "SUI", "XAU", "HYPE", "ADA", "TAO", "AVAX", "LINK", "XLM", "NEAR", "BNB", "SHIB", "FIL", "HBAR", "TON", "LTC", "ASTER", "WLD", "BCH", "LPT", "ARB", "NVDA", "TRX"], "best": ["XAU", "XAG", "FARTCOIN"]}, "4h": {"vwma": ["ETH", "SOL", "XRP", "DOGE", "RAY", "MASK", "ADA", "AVAX", "LINK", "XLM", "NEAR", "BNB", "ENA", "SHIB", "DOT", "FIL", "ENJ", "ONDO", "CRV", "HBAR", "SAND", "VIRTUAL", "LTC", "FARTCOIN", "MIRA", "SOON", "UNI", "BCH", "BAN"], "channel": ["BTC", "XAUT", "XRP", "TRUMP", "XAU", "XAG", "XLM", "BNB", "LTC", "ASTER", "EDGE", "NVDA", "MSTR", "TRX"], "best": ["BTC", "XAU", "ASTER"]}}