{"1h": {"vwma": ["BTC", "ETH", "XAU", "SOL", "XAG", "XRP", "PEPE", "XAUT", "DOGE", "TSLA", "SUI", "PAXG", "ZEC", "TRUMP", "CL", "NVDA", "MSTR", "BNB", "FARTCOIN", "JTO", "AAVE", "WLD", "AVAX", "AAPL", "WIF", "BCH", "AMZN", "ASTER", "SHIB", "1000BONK", "SAHARA", "ZRO", "WLFI", "HOOD", "HBAR", "LTC", "DYDX", "ICP", "TRX", "BANANAS31", "ATH", "GALA", "ETHFI"], "channel": ["TSLA", "NVDA", "NEAR", "DOT", "MU", "AAPL", "BCH", "AMZN", "GOOGL", "WLFI", "SIGN", "CYS", "EWY", "MSFT", "PIXEL", "META"], "best": ["XAG", "SIGN", "ICP", "PIXEL"]}, "4h": {"vwma": ["BTC", "ETH", "SOL", "PEPE", "DOGE", "ADA", "LINK", "MSTR", "BNB", "VIRTUAL", "PENGU", "FIL", "BCH", "AMZN", "1000BONK", "ZRO", "WLFI", "HBAR", "LTC", "DYDX", "ONDO", "ARC", "INTC"], "channel": ["RIVER", "COIN", "DOT", "MU", "BCH", "GOOGL", "TRX", "AKT", "MSFT"], "best": ["PIPPIN", "COIN", "MU", "GOOGL", "MSFT"]}}