{"1h": {"vwma": ["BTC", "ETH", "SKHYNIX", "KORU", "SOL", "XAU", "MU", "XRP", "XAG", "ZEC", "DRAM", "BZ", "DOGE", "SUI", "WLD", "MSTR", "XAUT", "QQQ", "UNI", "LINK", "EWY", "TSEM", "AAVE", "GLW", "AVAX", "RAM", "BNB", "AMD", "ENA", "PAXG", "PLTR", "PUMP", "UVXY", "INJ", "JTO", "FLNC", "XPL", "BEAT"], "channel": ["XAU", "XAUT", "CBRS", "QQQ", "CRCL", "NVDA", "BNB", "PAXG", "NATGAS", "MSFT", "TSLA", "ORCL", "META", "ARM", "TRX", "IREN", "SPY", "TRUMP"], "best": []}, "4h": {"vwma": ["BTC", "XAU", "BILL", "WLD", "MSTR", "XAUT", "QQQ", "SXT", "NVDA", "BNB", "AMD", "PAXG", "PLTR", "MSFT", "FIL", "TIA", "TRX", "SPY", "M"], "channel": ["BTC", "XAU", "HYPE", "XAUT", "QQQ", "TAO", "NVDA", "PI", "BCH", "PAXG", "ONDO", "NATGAS", "MSFT", "FIL", "ORCL", "ARM", "TRX", "SPY"], "best": ["ETH", "XRP", "XAG", "HYPE", "BILL", "DOGE", "SUI", "MSTR", "CRCL", "LINK", "NVDA", "IBM", "BNB", "MINIMAX", "SYN", "PLTR", "ONDO", "NATGAS", "ORCL", "DOT", "ARM", "SPY", "M"]}}