{"1h": {"vwma": ["XAUT", "EUL", "ASTER", "PAXG", "LINEA", "XAU", "WLFI", "RESOLV", "TRUMP", "XVG", "LIT", "BEAT", "DOLO", "KAS", "ZKP", "OPEN", "CHZ", "AIXBT"], "channel": ["BTC", "SOL", "XRP", "XAUT", "PEPE", "0G", "DOGE", "ZEC", "ASTER", "SUI", "PAXG", "ADA", "SAND", "XAU", "ENA", "WLFI", "LINK", "ZEN", "XPL", "FARTCOIN", "ZRO", "WLD", "TAO", "AVAX", "LTC", "TRUMP", "VIRTUAL", "APT", "XVG", "MMT", "DOT", "BNB", "BCH", "HBAR", "ICP", "NEAR", "FIL", "ONDO", "PENGU", "POWER", "2Z", "SHIB", "UNI", "BIO", "FET", "TRX", "PNUT", "DYDX", "GALA", "CRV"], "best": ["BTC", "0G", "WLD", "BNB", "BCH", "PENGU", "FET", "DYDX", "GALA", "CRV"]}, "4h": {"vwma": ["0G", "PUMP", "EUL", "SHELL", "WLFI", "2Z", "OPEN"], "channel": ["BTC", "BNB", "BERA", "TRX"], "best": []}}