{"1h": {"vwma": ["ETH", "SAND", "BNB", "CHZ", "LTC", "HYPE", "GALA", "BEAT", "PIPPIN", "TRX", "ARB", "LIT", "MOVE", "ID", "BGB", "IMX", "ACE"], "channel": ["ETH", "BTC", "SOL", "PUMP", "BNB", "CHZ", "AAVE", "CRV", "VIRTUAL", "BCH", "TRX", "TRUMP", "BGB"], "best": ["PROM", "WLFI", "MOVE"]}, "4h": {"vwma": ["BTC", "SOL", "LINK", "HYPE", "FIL", "DOT", "AAVE", "RARE", "CRV", "MET", "BLUR", "ARB", "GUN", "TIA", "H"], "channel": ["BTC", "SOL", "BNB", "NEAR", "FARTCOIN", "TAO", "BCH", "TRUMP", "POL", "GUN", "KAITO", "DYDX", "LDO", "CLO"], "best": ["RARE", "ACH", "LDO"]}}