{"1h": {"vwma": ["BTC", "ETH", "SOL", "XAU", "XRP", "XAUT", "HYPE", "DOGE", "PEPE", "SUI", "AAPL", "BNB", "PAXG", "NEAR", "LINK", "FARTCOIN", "GIGGLE", "RED", "AVAX", "STO", "ENA", "CRV", "SHIB", "BCH", "FIL", "BEAT", "GOOGL", "AMZN", "LTC", "OG", "ARB", "PUMP", "VIRTUAL", "ONDO", "TRX", "XLM", "UNI", "WIF", "ZBT", "TRUST", "CFX", "MON", "1000BONK", "ALGO"], "channel": ["XAU", "XAUT", "BLESS", "RIVER", "AAPL", "PAXG", "TRUMP", "WLD", "WLFI", "WET", "ASTER", "TRX", "TON"], "best": ["TSLA", "RIVER", "NVDA", "AAPL", "TRUMP", "BCH", "COIN", "TON", "MON"]}, "4h": {"vwma": ["SOL", "XAU", "XRP", "XAUT", "DOGE", "AAPL", "MYX", "BNB", "PAXG", "LINK", "AVAX", "CRV", "BEAT", "LTC", "TRX", "TON", "APT", "CFX", "1000BONK", "C"], "channel": ["XAU", "XAUT", "AAPL", "PAXG", "DOT", "FET", "ASTER", "RENDER"], "best": ["AAPL", "TRX"]}}