{"1h": {"vwma": ["SOL", "XRP", "ALLO", "WLD", "XAU", "DOGE", "XAUT", "ADA", "PEPE", "LINK", "NVDA", "XAG", "XPL", "SPCX", "TRUMP", "AVAX", "RKLB", "MSTR", "AAVE", "JTO", "PAXG", "APT", "PUMP", "WLFI", "LTC", "AAPL", "SHIB", "WIF", "QQQ", "PI"], "channel": ["XAU", "XAUT", "INTC", "PAXG", "AAPL", "GOOGL", "QQQ", "TSLA"], "best": ["SHIB"]}, "4h": {"vwma": ["ALLO", "NEAR", "ID", "XAU", "RENDER", "SEI", "INTC", "JTO", "PAXG", "GRASS", "PUMP", "IO", "AAPL", "QQQ", "ZAMA", "TSLA"], "channel": ["GENIUS", "TRX", "AAPL", "GOOGL", "QQQ"], "best": ["RENDER"]}}