{"1h": {"vwma": ["XAU", "XAUT", "KITE", "PAXG", "APT", "YGG", "WLD", "NVDA", "TRX", "TON"], "channel": ["BTC", "ETH", "SOL", "XAU", "XAG", "HYPE", "SUI", "BNB", "XAUT", "LINK", "BCH", "PAXG", "FARTCOIN", "ASTER", "HBAR", "AVAX", "XMR", "LTC", "INJ", "PUMP", "POWER", "SEI", "SOMI", "SNX", "TSLA", "FIL", "NVDA", "ONDO", "BGB", "AAPL", "MSTR", "AXS", "TRX", "IP", "COIN"], "best": ["AZTEC", "MYX"]}, "4h": {"vwma": ["XAU", "XAUT", "PAXG", "HBAR", "YGG", "INJ", "NVDA", "RENDER", "SAPIEN", "TRX"], "channel": ["BCH", "FARTCOIN", "ASTER", "HBAR", "TSLA", "ATOM", "TRX"], "best": ["FARTCOIN", "TSLA"]}}