{"1h": {"vwma": ["HYPE", "WLD", "MU", "SNDK", "RKLB", "CBRS", "XPL", "QQQ", "ETHFI", "AAVE", "ASTS", "TQQQ", "RDW", "LDO", "MAGMA", "KOPN", "CRDO", "IREN"], "channel": ["BTC", "ETH", "SPCX", "XAU", "SOL", "HYPE", "XRP", "XAG", "CL", "WLD", "XAUT", "SUI", "BZ", "PEPE", "TAO", "PAXG", "DOGE", "BNB", "QCOM", "LINK", "QQQ", "BCH", "INJ", "AAVE", "AVAX", "NVDA", "CRWV", "SPX", "TSLA", "DOT", "FET", "SPY", "SHIB", "XMR", "FIL", "PENGU", "LTC", "APT", "SEI"], "best": ["CL", "BZ", "INJ"]}, "4h": {"vwma": ["BTC", "ETH", "XRP", "ASTER", "H", "PEPE", "TAO", "ONDO", "QCOM", "LINK", "QQQ", "SPY", "AXTI", "LDO", "PENGU", "SEI", "COHR"], "channel": [], "best": []}}