{"4h": {"vwma": ["SAND", "BERA", "GOOGL", "MANA", "BIO", "CLO"], "channel": ["BTC", "ETH", "SOL", "HYPE", "MSTR", "LINK", "BNB", "XMR", "NVDA", "QQQ", "CRCL", "AAPL", "GOOGL", "NEAR", "ARB", "SLV", "COIN", "MSFT", "PLTR"], "best": ["ALCH", "MSFT"]}, "1h": {"vwma": ["XRP", "DOGE", "PEPE", "XAUT", "ADA", "MSTR", "TSLA", "BCH", "XAU", "PUMP", "PAXG", "NVDA", "QQQ", "HBAR", "GOOGL", "WIF", "RESOLV", "OP", "SHIB", "ACH", "DYDX", "FOGO", "POL", "META", "ATOM", "SAFE", "MANA", "BIO"], "channel": ["XAUT", "XAG", "XAU", "PAXG", "QQQ", "AAPL", "SLV", "COIN", "MSFT", "HOOD", "META", "PLTR"], "best": []}}