{"1h": {"vwma": ["XAU", "ARC", "XAUT", "PAXG", "ZRO", "JUP", "FORM", "ATH"], "channel": ["BTC", "XAU", "XAUT", "PAXG", "TAO", "ASTER", "GWEI", "HBAR", "SKYAI", "WLFI", "PI", "TSLA", "MORPHO", "BGB", "POL", "TON"], "best": ["BTC", "XAU", "ADA", "XAUT", "TAO", "LTC", "GWEI", "HBAR", "WLFI", "TSLA", "PNUT", "BGB", "POL", "TON"]}, "4h": {"vwma": ["GRASS", "BNB", "DENT", "SIREN", "ZRO", "VIRTUAL", "UNI", "KITE", "STEEM", "XMR", "JUP", "ICP", "FORM", "XPL", "ATH"], "channel": ["SHIB", "HBAR", "NVDA", "ETC", "WLFI", "TSLA", "RENDER", "INJ", "BGB", "POL", "TON"], "best": ["NVDA", "TON"]}}