{"1h": {"vwma": ["ETH", "SOL", "CLO", "POL", "BCH", "HYPER", "TAO", "BNB", "PUMP", "TRUMP", "CHZ", "AAVE", "B", "TRX", "XAUT", "RESOLV", "FORM", "DYDX", "ATOM", "PAXG", "PENDLE", "STX", "KAS"], "channel": ["BTC", "DOGE", "POL", "BNB", "HBAR", "LTC", "TRUMP", "NMR", "DOT", "TRX", "SHIB", "XAUT", "IRYS", "XLM", "GALA", "OP", "ARB", "ICP", "ATOM", "PAXG", "ETC"], "best": ["ETH", "SOL", "DOGE", "TAO", "BNB", "PIEVERSE", "HBAR", "LTC", "NMR", "DOT", "BREV", "TRX", "SHIB", "RESOLV", "XLM", "OP", "ARB", "ICP", "ETC"]}, "4h": {"vwma": ["BTC", "ETH", "HYPER", "ADA", "FARTCOIN", "BNB", "LINK", "GMT", "AVAX", "AKT", "TRUMP", "WLD", "FIL", "DOT", "NEAR", "TRX", "SHIB", "XAUT", "RESOLV", "WLFI", "GALA", "SEI", "ICP", "PAXG", "CTC"], "channel": ["BTC", "ETH", "SOL", "BNB", "LYN", "LINK", "HYPE", "AVAX", "HBAR", "ASTER", "LTC", "ENA", "XPL", "NMR", "WLD", "FIL", "DOT", "NEAR", "TRX", "ONDO", "APT", "WLFI", "OP", "ARB", "SEI", "ETC"], "best": ["LYN", "HYPE", "FIL"]}}