{"1h": {"vwma": ["XAU", "HYPE", "SAHARA", "DENT", "BNB", "XAUT", "ARB", "TAO", "PAXG", "MSTR", "NEAR", "VIRTUAL", "LTC", "FARTCOIN", "COIN", "UNI", "PENGU", "HBAR", "APT", "STEEM", "FOLKS", "XMR", "XPL", "GALA", "PLTR", "HOOD", "XLM", "GWEI", "CRV", "AXS", "SEI", "BERA", "PI", "WLFI", "MSFT"], "channel": ["BTC", "ETH", "SOL", "XRP", "XAU", "DOGE", "PEPE", "ADA", "NVDA", "LINK", "BNB", "ZEC", "AAVE", "XAUT", "TAO", "PAXG", "ENA", "KITE", "TSLA", "SHIB", "LTC", "ASTER", "PENGU", "HBAR", "STEEM", "XMR", "TRUMP", "WLD", "GOOGL", "ONDO", "BGB", "HOOD", "MU", "FET", "XLM", "CRV", "AXS", "SEI", "RENDER", "BERA", "AAPL", "PI", "WLFI", "POL", "ETC", "MSFT", "GRASS"], "best": ["ETH", "SOL", "XRP", "XAU", "DOGE", "PEPE", "PIPPIN", "DENT", "NVDA", "LINK", "ZEC", "MSTR", "SHIB", "COIN", "STEEM", "HOOD", "MU", "AAPL", "MSFT"]}, "4h": {"vwma": ["SAHARA", "ADA", "LINK", "BNB", "XAUT", "PAXG", "MSTR", "FIL", "KITE", "LTC", "HBAR", "STEEM", "XMR", "ATH", "WLD", "GOOGL", "XPL", "PLTR", "HOOD", "CRV", "RENDER", "AAPL", "PI", "WLFI", "POL", "NEWT", "GRASS"], "channel": ["PEPE", "PIPPIN", "NVDA", "BCH", "KITE", "TSLA", "SHIB", "ATOM"], "best": ["XAG", "SAHARA", "PIPPIN", "NVDA", "XAUT", "ATH", "HOOD", "NEWT"]}}