{"1h": {"vwma": ["BTC", "ETH", "SOL", "XAU", "DOGE", "SUI", "PEPE", "ADA", "LINK", "XAUT", "TSLA", "PAXG", "AVAX", "INX", "XMR", "LTC", "AAVE", "SHIB", "WLD", "ONDO", "1000BONK", "VANA", "XLM", "VIRTUAL", "DOT", "CRV", "ICP", "WIF", "ACU", "TON", "INJ"], "channel": ["XAU", "XAUT", "TSLA", "PAXG", "ENSO", "GOOGL", "IP", "SENT"], "best": ["BTC", "ETH", "SUI", "LINK", "XAUT", "INX", "NVDA", "ARB", "AMZN", "GOOGL", "VANA", "CRV", "ICP", "ACU", "TON", "SENT", "BGB"]}, "4h": {"vwma": ["HYPE", "XAU", "ASTER", "ARC", "NVDA"], "channel": ["AMZN", "GOOGL"], "best": ["AMZN", "GOOGL"]}}