{"1h": {"vwma": ["BTC", "ETH", "SOL", "CLO", "BCH", "BNB", "TAO", "VIRTUAL", "AKT", "CHZ", "TRUMP", "GUN", "XAUT", "B", "AVAX", "PENGU", "FET", "AAVE", "TRX", "DYDX", "INJ", "PAXG", "GIGGLE", "ATOM", "LIGHT", "M", "1000RATS", "KAITO"], "channel": ["BTC", "POL", "BCH", "PIPPIN", "BNB", "XAUT", "LTC", "IRYS", "SHIB", "TRX", "PAXG", "ATOM", "1000RATS", "KAITO"], "best": ["BTC", "ETH", "SOL", "POWER", "MUBARAK", "FET", "SHIB"]}, "4h": {"vwma": ["BTC", "ETH", "XRP", "PEPE", "ID", "DOGE", "BNB", "ADA", "GMT", "LINK", "NMR", "XAUT", "LTC", "ENA", "AVAX", "API3", "WLD", "BROCCOLI", "NEAR", "SHIB", "FIL", "TRX", "PAXG", "WLFI", "ARB", "SAHARA", "SEI", "CTC", "TON", "KAITO"], "channel": ["BTC", "ETH", "BNB", "POWER", "HYPE", "LINK", "ASTER", "NMR", "XPL", "LTC", "HBAR", "DOT", "AVAX", "NEAR", "FIL", "TRX", "APT", "WLFI", "ARB", "SEI", "TON"], "best": ["ZEC", "ADA", "POWER", "RENDER", "ENA", "AVAX", "API3", "SEI"]}}