{"1h": {"vwma": ["BTC", "ETH", "SOL", "TRUMP", "XRP", "HYPE", "DOGE", "SUI", "BANANAS31", "LINK", "BCH", "NEAR", "BNB", "FARTCOIN", "FIL", "SAHARA", "VIRTUAL", "AVAX", "HBAR", "ENA", "ASTER", "AXS", "XPL", "PENGU", "AAVE", "TRX", "GALA", "ICP", "OPN", "XLM", "CRV", "BERA", "MSTR", "NAORIS", "ARB", "UNI", "XMR", "ATH", "ONDO", "ARIA", "LTC", "WLFI", "SPK"], "channel": ["BTC", "ETH", "SOL", "XRP", "HYPE", "TSLA", "BCH", "XAU", "AAPL", "BNB", "NVDA", "SIGN", "AMZN", "XPL", "SHIB", "ENSO", "TRX", "XAUT", "1000BONK", "BERA", "MSTR", "NAORIS", "VVV", "UNI", "XMR", "H", "LTC", "WLFI", "PAXG", "POWER", "GRASS"], "best": ["SIGN", "ENSO", "PAXG", "GRASS"]}, "4h": {"vwma": ["SOL", "XRP", "DOGE", "ZEC", "BCH", "FARTCOIN", "SAHARA", "VIRTUAL", "ENA", "ASTER", "AXS", "SHIB", "AAVE", "LA", "1000BONK", "PUMP", "GALA", "MSTR", "VVV", "ARB", "UNI", "XMR", "ATH", "ONDO", "YGG", "LTC", "PLUME", "WLFI"], "channel": ["TSLA", "XAU", "AAPL", "RESOLV", "BEAT", "SIGN", "AMZN", "XAUT", "PAXG", "ZRO"], "best": ["AMZN", "NEO", "ATH", "PLUME"]}}