{"1h": {"vwma": ["BTC", "ETH", "HYPE", "ICP", "DOLO", "BNB", "BARD", "NVDA", "AXS", "ACH", "GOOGL", "ORDI", "BGB", "CRV", "POWER", "XVG", "TRX"], "channel": ["BTC", "ETH", "SOL", "XRP", "DOGE", "ZEC", "ADA", "SUI", "TSLA", "MSTR", "LINK", "ICP", "XAG", "PROM", "TAO", "WLD", "BNB", "ASTER", "FIL", "DOT", "AVAX", "AAPL", "NVDA", "UNI", "HBAR", "NEAR", "AAVE", "PENGU", "SEI", "XAUT", "TON", "HOOD", "WLFI", "ICNT", "XLM", "XAU", "POL", "SHIB", "GOOGL", "COIN", "CRCL", "APT", "COOKIE", "AMZN", "BGB", "CRV", "TRUMP", "RDDT", "AVNT", "DYDX", "OP", "ARB", "TRX", "USELESS"], "best": ["TSLA", "XAG", "NEAR", "XAUT", "ACH", "XAU", "COOKIE", "AMZN"]}, "4h": {"vwma": ["BTC", "MSTR", "LINK", "BNB", "FIL", "DOT", "NVDA", "XAUT", "WIF", "RENDER", "FET", "ICNT", "INJ", "XAU", "GOOGL", "CRV", "4"], "channel": ["SOL", "LTC", "SUI", "BCH", "KAITO", "WLD", "BNB", "BARD", "DOT", "AVAX", "AAPL", "NEAR", "SEI", "HOOD", "RENDER", "FET", "WLFI", "POL", "GOOGL", "COIN", "APT", "CLO", "AMZN", "TRUMP", "DYDX", "META", "TRX", "USELESS"], "best": ["HOOD", "POL", "USELESS"]}}