{"1h": {"vwma": ["ETH", "SAND", "BNB", "LTC", "HYPE", "GALA", "BEAT", "PIPPIN", "TRX", "ID", "LIT", "BIGTIME", "IMX", "BGB", "ACE", "XVG"], "channel": ["ETH", "BTC", "SOL", "PUMP", "BNB", "AAVE", "CRV", "VIRTUAL", "BCH", "TRX", "TRUMP", "BGB"], "best": ["CRV", "BCH", "PENGU", "DRIFT", "XVG"]}, "4h": {"vwma": ["BTC", "SOL", "LINK", "HYPE", "FIL", "AAVE", "RARE", "CRV", "MET", "ARB", "BLUR", "GUN", "H", "TIA", "CLO"], "channel": ["BTC", "SOL", "BNB", "NEAR", "TAO", "TRUMP", "POL", "GUN", "PROM", "KAITO", "DYDX", "LDO"], "best": ["RARE", "ACH", "LDO"]}}