{"1h": {"vwma": ["BTC", "ETH", "SOL", "XRP", "XAG", "XAU", "DOGE", "SUI", "TSLA", "ADA", "TAO", "MSTR", "ZEC", "SIGN", "LINK", "XAUT", "NVDA", "RESOLV", "SHIB", "PAXG", "BNB", "NEAR", "AVAX", "BCH", "FARTCOIN", "PUMP", "VIRTUAL", "PENGU", "AAPL", "XPL", "AAVE", "PI", "XLM", "DOT", "POWER", "OPN", "HOOD", "LTC", "1000BONK", "UNI", "AMZN", "SAHARA", "ARB", "TIA", "ONDO", "META", "XMR", "WLFI", "ZRO", "GOOGL"], "channel": ["XRP", "XAU", "TAO", "FIL", "XAUT", "PAXG", "BCH", "AAPL", "PLTR", "ASTER", "LTC", "ROBO", "APT", "HBAR", "MYX", "MSFT", "ZRO"], "best": ["TAO", "ZEC", "RESOLV", "WIF", "ICP", "OPN", "ZRO"]}, "4h": {"vwma": ["BTC", "ETH", "SOL", "XRP", "XAG", "XAU", "TSLA", "MSTR", "LINK", "NVDA", "BNB", "VIRTUAL", "PENGU", "KITE", "MU", "XLM", "HOOD", "FET", "ARM", "UNI", "AMZN", "SAHARA", "TIA", "META", "MSFT", "GOOGL"], "channel": ["FIL", "PLTR", "WLD", "HBAR", "SEI", "MSFT"], "best": ["FIL", "ICP"]}}