{"1h": {"vwma": ["BTC", "SOL", "XAG", "XAU", "HYPE", "XAUT", "PAXG", "BNB", "SIREN", "AAVE", "VIRTUAL", "TRUMP", "UNI", "APT", "PENGU", "XMR", "ARB", "OP", "SPX", "TIA", "SEI", "XPL", "MORPHO"], "channel": ["XAG", "XAU", "XAUT", "PAXG", "TSLA", "ASTER", "TON", "PI", "WLFI", "BGB", "HOOD", "TRX"], "best": ["TRUMP", "PI"]}, "4h": {"vwma": ["SOL", "XAUT", "BNB", "DENT", "MSTR", "APT", "ARB", "STEEM", "SPX", "ICP", "XPL", "BEAT"], "channel": ["TSLA", "KITE", "NVDA", "WLFI", "BGB", "TRX", "POL"], "best": ["TSLA", "TRX"]}}