{"1h": {"vwma": ["ETH", "SOL", "XAG", "XAU", "HYPE", "DOT", "LINK", "BNB", "MYX", "TAO", "ENA", "NEAR", "XAUT", "PUMP", "WET", "MSTR", "LTC", "FARTCOIN", "UNI", "HBAR", "COIN", "STEEM", "PENGU", "PAXG", "XMR", "WLD", "OP", "GWEI", "GRASS", "XPL", "MSFT", "SEI", "CRV", "XLM", "GALA", "WLFI", "PI", "RENDER", "HOOD", "AXS", "ETC", "PLTR"], "channel": ["BTC", "ETH", "XRP", "XAG", "XAU", "DOGE", "PEPE", "NVDA", "ZEC", "BNB", "TAO", "KITE", "XAUT", "SHIB", "TSLA", "ASTER", "GOOGL", "HBAR", "STEEM", "PAXG", "XMR", "WLD", "TRUMP", "UAI", "BGB", "MU", "MSFT", "AAPL", "XLM", "PI", "POL"], "best": ["BTC", "ETH", "ZEC", "BNB", "XAUT", "BGB", "XPL"]}, "4h": {"vwma": ["SOL", "XAU", "ADA", "LINK", "BNB", "TAO", "KITE", "FIL", "ARB", "XAUT", "MSTR", "LTC", "HBAR", "STEEM", "PENGU", "PAXG", "XMR", "WLD", "XPL", "AAPL", "CRV", "WLFI", "RENDER", "HOOD", "POL", "PLTR"], "channel": ["NVDA", "BCH", "KITE", "SHIB", "TSLA", "ATOM", "TRUMP", "UAI", "GPS"], "best": ["ARB"]}}