{"1h": {"vwma": ["WLFI", "ONDO", "WLD", "ENA", "LITE", "NVDA", "UNI", "AAVE", "LAB", "ZHIPU", "EWY", "LTC", "AAOI", "HBAR", "TSM", "TRUMP", "EVAA", "BX", "BE", "IREN", "RKLB", "CRWV"], "channel": ["BTC", "ETH", "SNDK", "SOL", "MU", "SKHYNIX", "XRP", "XAU", "XAG", "HYPE", "DOGE", "DRAM", "ZEC", "SUI", "XAUT", "GOOGL", "MRVL", "ONDO", "ADA", "PEPE", "QQQ", "CRCL", "ENA", "LITE", "NVDA", "XLM", "O", "NBIS", "UNI", "MSTR", "AAVE", "AMD", "LINK", "AVAX", "SAMSUNG", "TAO", "EWY", "AMZN", "LTC", "PAXG", "MSFT", "AAOI", "BNB", "HBAR", "1000BONK", "TSM", "TIA", "AAPL", "JTO", "FIL", "DOT", "BCH", "PLTR", "COIN", "IREN", "CRWV", "PENGU", "INJ"], "best": ["ETH", "MU", "DOGE", "INTC", "WLD", "CRCL", "AVAX", "LTC", "DOT", "PLTR", "PENGU", "INJ"]}, "4h": {"vwma": ["BTC", "ETH", "SNDK", "SOXL", "XRP", "DRAM", "SUI", "WLFI", "ADA", "PEPE", "RE", "NVDA", "AAVE", "SAMSUNG", "EWY", "AAOI", "ARM", "JTO", "TRUMP", "BX", "CRWV", "INJ"], "channel": ["BTC", "ETH", "DOGE", "ZEC", "XAUT", "PEPE", "QQQ", "O", "LINK", "AVAX", "MSFT", "BNB", "AAPL", "FIL", "DOT", "PLTR", "BX", "INJ"], "best": ["DOGE", "DEXE", "INTC", "PEPE", "MSFT", "ARM", "PLTR"]}}