{"1h": {"vwma": ["BTC", "ETH", "SOL", "DOGE", "ADA", "HYPE", "MSTR", "ASTER", "LINK", "XAG", "FIL", "AVAX", "BNB", "HBAR", "XAUT", "AAVE", "NEAR", "DOT", "WIF", "PENGU", "AAPL", "WLD", "CRCL", "MOVE", "XAU", "ORDI", "PAXG", "CLO", "ARB", "SAFE", "GOOGL", "KGEN", "ZK", "OP", "APT", "BGB", "COIN", "GALA", "JUP", "CRV", "SLV", "ETC", "TRX", "TIA", "HOOD"], "channel": ["BTC", "SOL", "XRP", "DOGE", "SUI", "LTC", "ADA", "XMR", "HYPE", "FARTCOIN", "LINK", "XAG", "TAO", "TSLA", "AVAX", "BNB", "UNI", "XAUT", "AAVE", "NEAR", "AAPL", "WLFI", "NVDA", "ONDO", "CRCL", "FET", "SHIB", "TRUMP", "USELESS", "XAU", "PAXG", "GOOGL", "SEI", "BGB", "CHZ", "COIN", "SLV", "PNUT", "REZ", "AMZN", "JASMY", "TRX", "HOOD"], "best": ["UNI"]}, "4h": {"vwma": ["DOGE", "SUI", "ADA", "ASTER", "FARTCOIN", "AVAX", "HBAR", "XAUT", "XLM", "VIRTUAL", "RENDER", "WLFI", "WLD", "CRCL", "SHIB", "TRUMP", "XAU", "PAXG", "ARB", "SEI", "ZK", "COIN", "METIS", "CRV", "ETC", "REZ", "HOOD"], "channel": ["BCH", "LTC", "TAO", "RENDER", "WLFI", "NVDA", "TRUMP", "AMZN", "TRX"], "best": ["BCH", "AMZN"]}}