{"1h": {"vwma": ["BCH", "FOLKS", "PI", "TRX", "TURBO", "ORDER", "AKT", "ANIME", "CL", "XMR"], "channel": ["BTC", "XRP", "SUI", "BNB", "APT", "LTC", "SAHARA", "PI", "DOT", "NVDA", "SHIB", "TRX", "HBAR", "GALA", "RESOLV", "ARB", "JD", "CRV", "XLM", "ATH", "IP", "ICP", "SEI", "AMZN", "ARC"], "best": ["APT", "NVDA", "TRX"]}, "4h": {"vwma": ["HYPE", "MAGMA", "BCH", "ANKR", "VVV"], "channel": ["BTC", "ETH", "SOL", "XRP", "HYPE", "DOGE", "XAU", "SUI", "ADA", "TSLA", "LINK", "BNB", "ASTER", "PENGU", "AVAX", "LTC", "XAUT", "DOT", "NVDA", "SHIB", "MSTR", "AAVE", "PUMP", "HBAR", "GALA", "PAXG", "ARB", "JD", "CRCL", "UNI", "CRV", "NAORIS", "TIA", "RENDER", "XLM", "GRASS", "ZRO", "IP", "ICP", "ONDO", "SEI", "AMZN"], "best": ["XAU", "TSLA", "XAUT", "NVDA", "TRX", "GALA", "PAXG", "JD", "UNI", "XPL", "CRV", "GRASS"]}}