{"4h": {"vwma": ["TSLA", "GOOGL", "QQQ", "META", "WLFI", "PENDLE", "ARC"], "channel": ["BTC", "ETH", "SOL", "MSTR", "LINK", "AVAX", "GOOGL", "BNB", "AAPL", "ARB", "QQQ", "CRCL", "CHZ", "AAVE", "COIN", "TRX", "FIL", "PLTR", "CRV"], "best": ["ETH", "TSLA", "CRV"]}, "1h": {"vwma": ["XAUT", "ZEC", "XAG", "MSTR", "XAU", "NVDA", "BCH", "GOOGL", "PAXG", "AAPL", "RESOLV", "0G", "QQQ", "MANA", "SAFE", "SLV"], "channel": ["XAUT", "XAU", "PAXG", "AAPL", "BARD", "QQQ", "ARC", "COIN", "PLTR"], "best": ["BERA"]}}