{"1h": {"vwma": ["CRCL", "IP", "TRX"], "channel": ["BTC", "ETH", "SOL", "XAU", "XRP", "BNB", "DOGE", "XAUT", "TAO", "CRCL", "ZEC", "SUI", "TSLA", "PAXG", "ADA", "COIN", "LINK", "BCH", "MSTR", "MU", "ASTER", "FIL", "NEAR", "APT", "AVAX", "FET", "ENA", "DOT", "ETHFI", "LTC", "AAVE", "PUMP", "VIRTUAL", "NVDA", "PENGU", "UNI", "XPL", "KITE", "PLTR", "NXPC", "ONDO", "SHIB", "GALA", "IP", "AAPL", "1000BONK", "XLM", "RENDER", "AXS", "WIF", "HBAR", "ARB", "ETC", "TRX", "AMZN", "H", "ZRO", "XMR", "CRV", "HOOD", "META", "WLFI", "TIA"], "best": ["XAU", "XAUT", "TAO", "AAPL", "H", "WLFI"]}, "4h": {"vwma": ["ETH", "SOL", "XRP", "ENJ", "ADA", "COIN", "SAHARA", "NEAR", "APT", "DOT", "AAVE", "ZRO", "TIA"], "channel": ["BTC", "XAU", "XAG", "BNB", "XAUT", "SUI", "TSLA", "PAXG", "LINK", "BCH", "MSTR", "ASTER", "AVAX", "ETHFI", "LTC", "PUMP", "NVDA", "PENGU", "PLTR", "NXPC", "AAPL", "HBAR", "TRX", "AMZN", "ZRO", "XMR", "META", "TIA"], "best": ["BTC", "XAU", "XAG", "BNB", "XAUT", "SUI", "PAXG", "PUMP", "NVDA", "PENGU", "ARIA", "HBAR", "XMR", "TIA"]}}