{"1h": {"vwma": ["BTC", "ETH", "SOL", "CRCL", "DOGE", "SUI", "PEPE", "TRUMP", "LINK", "ADA", "NVDA", "BNB", "ICP", "AVAX", "PUMP", "AAVE", "SHIB", "ENA", "BCH", "FARTCOIN", "DOT", "PENGU", "VIRTUAL", "MU", "ARIA", "UNI", "LTC", "XLM", "1000BONK", "TIA", "GOOGL", "BARD", "ARB", "SEI", "ZRO", "ONDO", "BIRB", "TRX"], "channel": ["BTC", "ETH", "SOL", "XRP", "XAG", "XAU", "HYPE", "SUI", "TSLA", "PEPE", "MSTR", "XAUT", "LINK", "ADA", "ZEC", "NVDA", "PAXG", "BNB", "AAPL", "NEAR", "AVAX", "AAVE", "COIN", "SHIB", "ENA", "BCH", "FARTCOIN", "ASTER", "APT", "DOT", "PENGU", "AMZN", "MU", "GALA", "ARIA", "HOOD", "CRV", "UNI", "LTC", "XLM", "1000BONK", "TIA", "GOOGL", "ORCL", "ARB", "XPT", "HBAR", "ZRO", "ONDO", "BIRB", "TRX"], "best": ["XAG", "XAU", "TRUMP", "XAUT", "PAXG"]}, "4h": {"vwma": ["BTC", "ETH", "SOL", "DOGE", "MSTR", "LINK", "SIGN", "XPL", "MMT", "COIN", "SHIB", "PENGU", "VIRTUAL", "MU", "UNI", "XLM", "1000BONK", "TIA", "ORCL", "ARC", "TRX"], "channel": ["XAU", "TSLA", "XAUT", "PLTR", "PAXG", "AAPL", "COIN", "APT", "AMZN", "HOOD", "APP", "TRX"], "best": ["XAU", "XAUT", "PAXG", "FIL", "APT", "AMZN", "HOOD"]}}